blanc_seo-0.2.dist-info/DESCRIPTION.rst
blanc_seo-0.2.dist-info/METADATA
blanc_seo-0.2.dist-info/RECORD
blanc_seo-0.2.dist-info/WHEEL
blanc_seo-0.2.dist-info/metadata.json
blanc_seo-0.2.dist-info/top_level.txt
blancseo/__init__.py
blancseo/admin.py
blancseo/apps.py
blancseo/context_processors.py
blancseo/models.py
blancseo/tests.py
blancseo/views.py
blancseo/migrations/0001_initial.py
blancseo/migrations/__init__.py
blancseo/templates/seo.html
blancseo/templatetags/__init__.py
blancseo/templatetags/seo_tags.py
